halting/__init__.py
halting/config.py
halting/tests.py
halting/figures/__init__.py
halting/figures/numbers.py
halting/figures/tests.py
halting/figures/tests/numbers.py
halting/formulas/__init__.py
halting/formulas/formulas.py
halting/formulas/tests/formulas.py
halting/length/__init__.py
halting/length/length.py
halting/length/tests.py
halting/length/tests/length.py
halting/mass/__init__.py
halting/mass/mass.py
halting/mass/tests.py
halting/mass/tests/mass.py
halting/time/__init__.py
halting/time/tests.py
halting/time/time.py
halting/time/tests/time.py
halting-1.0.0.dist-info/.gitignore
halting-1.0.0.dist-info/LICENSE.txt
halting-1.0.0.dist-info/METADATA
halting-1.0.0.dist-info/WHEEL
halting-1.0.0.dist-info/top_level.txt
halting-1.0.0.dist-info/RECORD
