Metadata-Version: 2.1
Name: halting
Version: 1.0.0
Summary: Physics Library to manage physical units.
Author-email: João Vitor Witt <joaovitorwitt2004@gmail.com>
License: MIT License
Project-URL: Homepage, https://github.com/joaovitorwitt/physics-lib
Project-URL: Issues, https://github.com/joaovitorwitt/physics-lib/issues
Project-URL: Pulls, https://github.com/joaovitorwitt/physics-lib/pulls
Keywords: python,physics,lib,development
Requires-Python: >=3.0
License-File: LICENSE.txt
